{"version":1,"timestamp":1763257779,"plugins":{"access-matrix":{"downloads_url":"plugins/access-matrix.json"},"cluster-group":{"downloads_url":"plugins/cluster-group.json"},"capture":{"downloads_url":"plugins/capture.json"},"browse-pvc":{"downloads_url":"plugins/browse-pvc.json"},"accurate":{"downloads_url":"plugins/accurate.json"},"cm":{"downloads_url":"plugins/cm.json"},"advise-psp":{"downloads_url":"plugins/advise-psp.json"},"ca-cert":{"downloads_url":"plugins/ca-cert.json"},"clusternet":{"downloads_url":"plugins/clusternet.json"},"assert":{"downloads_url":"plugins/assert.json"},"cnpg":{"downloads_url":"plugins/cnpg.json"},"autons":{"downloads_url":"plugins/autons.json"},"actuator":{"downloads_url":"plugins/actuator.json"},"allctx":{"downloads_url":"plugins/allctx.json"},"alfred":{"downloads_url":"plugins/alfred.json"},"blame":{"downloads_url":"plugins/blame.json"},"bd-xray":{"downloads_url":"plugins/bd-xray.json"},"colorize-applied":{"downloads_url":"plugins/colorize-applied.json"},"apparmor-manager":{"downloads_url":"plugins/apparmor-manager.json"},"apidocs":{"downloads_url":"plugins/apidocs.json"},"auth-proxy":{"downloads_url":"plugins/auth-proxy.json"},"aks":{"downloads_url":"plugins/aks.json"},"cache":{"downloads_url":"plugins/cache.json"},"argo-apps-viz":{"downloads_url":"plugins/argo-apps-viz.json"},"azad-proxy":{"downloads_url":"plugins/azad-proxy.json"},"advise-policy":{"downloads_url":"plugins/advise-policy.json"},"armadactl":{"downloads_url":"plugins/armadactl.json"},"cnf":{"downloads_url":"plugins/cnf.json"},"ai":{"downloads_url":"plugins/ai.json"},"cautious":{"downloads_url":"plugins/cautious.json"},"change-ns":{"downloads_url":"plugins/change-ns.json"},"clog":{"downloads_url":"plugins/clog.json"},"cond":{"downloads_url":"plugins/cond.json"},"bulk-action":{"downloads_url":"plugins/bulk-action.json"},"cert-manager":{"downloads_url":"plugins/cert-manager.json"},"applier":{"downloads_url":"plugins/applier.json"},"cluster-compare":{"downloads_url":"plugins/cluster-compare.json"},"commatrix":{"downloads_url":"plugins/commatrix.json"},"cilium":{"downloads_url":"plugins/cilium.json"},"aws-auth":{"downloads_url":"plugins/aws-auth.json"},"cnp-viz":{"downloads_url":"plugins/cnp-viz.json"},"conditioner":{"downloads_url":"plugins/conditioner.json"},"config-cleanup":{"downloads_url":"plugins/config-cleanup.json"},"community-images":{"downloads_url":"plugins/community-images.json"},"colorize-managed-fields":{"downloads_url":"plugins/colorize-managed-fields.json"},"commander":{"downloads_url":"plugins/commander.json"},"config-doctor":{"downloads_url":"plugins/config-doctor.json"},"cost":{"downloads_url":"plugins/cost.json"},"cleaner":{"downloads_url":"plugins/cleaner.json"},"crashwatch":{"downloads_url":"plugins/crashwatch.json"},"crane":{"downloads_url":"plugins/crane.json"},"crd-wizard":{"downloads_url":"plugins/crd-wizard.json"},"crust-gather":{"downloads_url":"plugins/crust-gather.json"},"count":{"downloads_url":"plugins/count.json"},"creyaml":{"downloads_url":"plugins/creyaml.json"},"ctr":{"downloads_url":"plugins/ctr.json"},"config-registry":{"downloads_url":"plugins/config-registry.json"},"cpbase64":{"downloads_url":"plugins/cpbase64.json"},"confirm":{"downloads_url":"plugins/confirm.json"},"config-import":{"downloads_url":"plugins/config-import.json"},"df-pv":{"downloads_url":"plugins/df-pv.json"},"cs":{"downloads_url":"plugins/cs.json"},"dds":{"downloads_url":"plugins/dds.json"},"cwide":{"downloads_url":"plugins/cwide.json"},"ctx":{"downloads_url":"plugins/ctx.json"},"deprecations":{"downloads_url":"plugins/deprecations.json"},"custom-cols":{"downloads_url":"plugins/custom-cols.json"},"duck":{"downloads_url":"plugins/duck.json"},"dup":{"downloads_url":"plugins/dup.json"},"ctx-tags":{"downloads_url":"plugins/ctx-tags.json"},"cypher":{"downloads_url":"plugins/cypher.json"},"dpm":{"downloads_url":"plugins/dpm.json"},"doctor":{"downloads_url":"plugins/doctor.json"},"dumpy":{"downloads_url":"plugins/dumpy.json"},"directpv":{"downloads_url":"plugins/directpv.json"},"discover":{"downloads_url":"plugins/discover.json"},"cyclonus":{"downloads_url":"plugins/cyclonus.json"},"eksporter":{"downloads_url":"plugins/eksporter.json"},"encrypted-kubeconfig":{"downloads_url":"plugins/encrypted-kubeconfig.json"},"datadog":{"downloads_url":"plugins/datadog.json"},"exec-cronjob":{"downloads_url":"plugins/exec-cronjob.json"},"debug-shell":{"downloads_url":"plugins/debug-shell.json"},"debug-pdb":{"downloads_url":"plugins/debug-pdb.json"},"example":{"downloads_url":"plugins/example.json"},"execws":{"downloads_url":"plugins/execws.json"},"envsubst":{"downloads_url":"plugins/envsubst.json"},"explore":{"downloads_url":"plugins/explore.json"},"exec-as":{"downloads_url":"plugins/exec-as.json"},"emit-event":{"downloads_url":"plugins/emit-event.json"},"evict-pod":{"downloads_url":"plugins/evict-pod.json"},"fleet":{"downloads_url":"plugins/fleet.json"},"datree":{"downloads_url":"plugins/datree.json"},"envx":{"downloads_url":"plugins/envx.json"},"fields":{"downloads_url":"plugins/fields.json"},"flame":{"downloads_url":"plugins/flame.json"},"eds":{"downloads_url":"plugins/eds.json"},"gadget":{"downloads_url":"plugins/gadget.json"},"graph":{"downloads_url":"plugins/graph.json"},"foreach":{"downloads_url":"plugins/foreach.json"},"fd":{"downloads_url":"plugins/fd.json"},"gs":{"downloads_url":"plugins/gs.json"},"edit-status":{"downloads_url":"plugins/edit-status.json"},"health":{"downloads_url":"plugins/health.json"},"duplicate":{"downloads_url":"plugins/duplicate.json"},"hlf":{"downloads_url":"plugins/hlf.json"},"fuzzy":{"downloads_url":"plugins/fuzzy.json"},"http":{"downloads_url":"plugins/http.json"},"gopass":{"downloads_url":"plugins/gopass.json"},"grep":{"downloads_url":"plugins/grep.json"},"flyte":{"downloads_url":"plugins/flyte.json"},"history":{"downloads_url":"plugins/history.json"},"htpasswd":{"downloads_url":"plugins/htpasswd.json"},"kadalu":{"downloads_url":"plugins/kadalu.json"},"iexec":{"downloads_url":"plugins/iexec.json"},"ingress-nginx":{"downloads_url":"plugins/ingress-nginx.json"},"get-all":{"downloads_url":"plugins/get-all.json"},"ip-check":{"downloads_url":"plugins/ip-check.json"},"kamaji":{"downloads_url":"plugins/kamaji.json"},"ipick":{"downloads_url":"plugins/ipick.json"},"ingress-rule":{"downloads_url":"plugins/ingress-rule.json"},"insider":{"downloads_url":"plugins/insider.json"},"kaito":{"downloads_url":"plugins/kaito.json"},"karmada":{"downloads_url":"plugins/karmada.json"},"gke-credentials":{"downloads_url":"plugins/gke-credentials.json"},"image":{"downloads_url":"plugins/image.json"},"gke-policy":{"downloads_url":"plugins/gke-policy.json"},"karbon":{"downloads_url":"plugins/karbon.json"},"ice":{"downloads_url":"plugins/ice.json"},"kjob":{"downloads_url":"plugins/kjob.json"},"janitor":{"downloads_url":"plugins/janitor.json"},"kluster-capacity":{"downloads_url":"plugins/kluster-capacity.json"},"knife":{"downloads_url":"plugins/knife.json"},"kimspect":{"downloads_url":"plugins/kimspect.json"},"kc":{"downloads_url":"plugins/kc.json"},"komodor":{"downloads_url":"plugins/komodor.json"},"kollama":{"downloads_url":"plugins/kollama.json"},"kopilot":{"downloads_url":"plugins/kopilot.json"},"images":{"downloads_url":"plugins/images.json"},"ks":{"downloads_url":"plugins/ks.json"},"kubetail":{"downloads_url":"plugins/kubetail.json"},"lineage":{"downloads_url":"plugins/lineage.json"},"kudo":{"downloads_url":"plugins/kudo.json"},"kubesec-scan":{"downloads_url":"plugins/kubesec-scan.json"},"konfig":{"downloads_url":"plugins/konfig.json"},"kor":{"downloads_url":"plugins/kor.json"},"klock":{"downloads_url":"plugins/klock.json"},"krew":{"downloads_url":"plugins/krew.json"},"ktop":{"downloads_url":"plugins/ktop.json"},"kuota-calc":{"downloads_url":"plugins/kuota-calc.json"},"kubescape":{"downloads_url":"plugins/kubescape.json"},"marvin":{"downloads_url":"plugins/marvin.json"},"kurt":{"downloads_url":"plugins/kurt.json"},"kyverno":{"downloads_url":"plugins/kyverno.json"},"lock":{"downloads_url":"plugins/lock.json"},"mapr-ticket":{"downloads_url":"plugins/mapr-ticket.json"},"linstor":{"downloads_url":"plugins/linstor.json"},"link":{"downloads_url":"plugins/link.json"},"liqo":{"downloads_url":"plugins/liqo.json"},"log2rbac":{"downloads_url":"plugins/log2rbac.json"},"istiolog":{"downloads_url":"plugins/istiolog.json"},"mounts":{"downloads_url":"plugins/mounts.json"},"mc":{"downloads_url":"plugins/mc.json"},"meshsync-snapshot":{"downloads_url":"plugins/meshsync-snapshot.json"},"mdba":{"downloads_url":"plugins/mdba.json"},"minio":{"downloads_url":"plugins/minio.json"},"moco":{"downloads_url":"plugins/moco.json"},"mtv":{"downloads_url":"plugins/mtv.json"},"neat":{"downloads_url":"plugins/neat.json"},"mexec":{"downloads_url":"plugins/mexec.json"},"netobserv":{"downloads_url":"plugins/netobserv.json"},"multiforward":{"downloads_url":"plugins/multiforward.json"},"node-shell":{"downloads_url":"plugins/node-shell.json"},"netscaler":{"downloads_url":"plugins/netscaler.json"},"node-resource":{"downloads_url":"plugins/node-resource.json"},"nodepools":{"downloads_url":"plugins/nodepools.json"},"multinet":{"downloads_url":"plugins/multinet.json"},"node-restart":{"downloads_url":"plugins/node-restart.json"},"node-ssm":{"downloads_url":"plugins/node-ssm.json"},"nodegizmo":{"downloads_url":"plugins/nodegizmo.json"},"ns":{"downloads_url":"plugins/ns.json"},"nginx-supportpkg":{"downloads_url":"plugins/nginx-supportpkg.json"},"operator":{"downloads_url":"plugins/operator.json"},"pickdeep":{"downloads_url":"plugins/pickdeep.json"},"passman":{"downloads_url":"plugins/passman.json"},"np-viewer":{"downloads_url":"plugins/np-viewer.json"},"match-name":{"downloads_url":"plugins/match-name.json"},"oidc-login":{"downloads_url":"plugins/oidc-login.json"},"node-logs":{"downloads_url":"plugins/node-logs.json"},"net-forward":{"downloads_url":"plugins/net-forward.json"},"modify-secret":{"downloads_url":"plugins/modify-secret.json"},"pod-logs":{"downloads_url":"plugins/pod-logs.json"},"nsenter":{"downloads_url":"plugins/nsenter.json"},"oadp":{"downloads_url":"plugins/oadp.json"},"plogs":{"downloads_url":"plugins/plogs.json"},"output":{"downloads_url":"plugins/output.json"},"node-admin":{"downloads_url":"plugins/node-admin.json"},"oomd":{"downloads_url":"plugins/oomd.json"},"pod-inspect":{"downloads_url":"plugins/pod-inspect.json"},"oulogin":{"downloads_url":"plugins/oulogin.json"},"permissions":{"downloads_url":"plugins/permissions.json"},"podevents":{"downloads_url":"plugins/podevents.json"},"preflight":{"downloads_url":"plugins/preflight.json"},"pods-on":{"downloads_url":"plugins/pods-on.json"},"outdated":{"downloads_url":"plugins/outdated.json"},"preq":{"downloads_url":"plugins/preq.json"},"pod-dive":{"downloads_url":"plugins/pod-dive.json"},"pod-shell":{"downloads_url":"plugins/pod-shell.json"},"profefe":{"downloads_url":"plugins/profefe.json"},"prune-unused":{"downloads_url":"plugins/prune-unused.json"},"prompt":{"downloads_url":"plugins/prompt.json"},"promdump":{"downloads_url":"plugins/promdump.json"},"portal":{"downloads_url":"plugins/portal.json"},"pexec":{"downloads_url":"plugins/pexec.json"},"open-svc":{"downloads_url":"plugins/open-svc.json"},"popeye":{"downloads_url":"plugins/popeye.json"},"pvmigrate":{"downloads_url":"plugins/pvmigrate.json"},"pv-migrate":{"downloads_url":"plugins/pv-migrate.json"},"print-env":{"downloads_url":"plugins/print-env.json"},"resource-backup":{"downloads_url":"plugins/resource-backup.json"},"reap":{"downloads_url":"plugins/reap.json"},"psp-util":{"downloads_url":"plugins/psp-util.json"},"resource-snapshot":{"downloads_url":"plugins/resource-snapshot.json"},"rbac-lookup":{"downloads_url":"plugins/rbac-lookup.json"},"resource-capacity":{"downloads_url":"plugins/resource-capacity.json"},"rabbitmq":{"downloads_url":"plugins/rabbitmq.json"},"resource-versions":{"downloads_url":"plugins/resource-versions.json"},"realname-diff":{"downloads_url":"plugins/realname-diff.json"},"rename-pvc":{"downloads_url":"plugins/rename-pvc.json"},"pv-mounter":{"downloads_url":"plugins/pv-mounter.json"},"reverse-proxy":{"downloads_url":"plugins/reverse-proxy.json"},"rbac-view":{"downloads_url":"plugins/rbac-view.json"},"rolesum":{"downloads_url":"plugins/rolesum.json"},"retina":{"downloads_url":"plugins/retina.json"},"restart":{"downloads_url":"plugins/restart.json"},"roll":{"downloads_url":"plugins/roll.json"},"saconfig":{"downloads_url":"plugins/saconfig.json"},"ray":{"downloads_url":"plugins/ray.json"},"rm-standalone-pods":{"downloads_url":"plugins/rm-standalone-pods.json"},"revisions":{"downloads_url":"plugins/revisions.json"},"secretdata":{"downloads_url":"plugins/secretdata.json"},"relay":{"downloads_url":"plugins/relay.json"},"rook-ceph":{"downloads_url":"plugins/rook-ceph.json"},"score":{"downloads_url":"plugins/score.json"},"sick-pods":{"downloads_url":"plugins/sick-pods.json"},"safe":{"downloads_url":"plugins/safe.json"},"rbac-tool":{"downloads_url":"plugins/rbac-tool.json"},"socks5-proxy":{"downloads_url":"plugins/socks5-proxy.json"},"spy":{"downloads_url":"plugins/spy.json"},"service-tree":{"downloads_url":"plugins/service-tree.json"},"slice":{"downloads_url":"plugins/slice.json"},"sgmap":{"downloads_url":"plugins/sgmap.json"},"ssh-jump":{"downloads_url":"plugins/ssh-jump.json"},"sql":{"downloads_url":"plugins/sql.json"},"shovel":{"downloads_url":"plugins/shovel.json"},"split-yaml":{"downloads_url":"plugins/split-yaml.json"},"sshd":{"downloads_url":"plugins/sshd.json"},"slowdrain":{"downloads_url":"plugins/slowdrain.json"},"sniff":{"downloads_url":"plugins/sniff.json"},"snap":{"downloads_url":"plugins/snap.json"},"strace":{"downloads_url":"plugins/strace.json"},"switch-config":{"downloads_url":"plugins/switch-config.json"},"tail":{"downloads_url":"plugins/tail.json"},"stern":{"downloads_url":"plugins/stern.json"},"shell-ctx":{"downloads_url":"plugins/shell-ctx.json"},"subm":{"downloads_url":"plugins/subm.json"},"sort-manifests":{"downloads_url":"plugins/sort-manifests.json"},"sudo":{"downloads_url":"plugins/sudo.json"},"track":{"downloads_url":"plugins/track.json"},"trace":{"downloads_url":"plugins/trace.json"},"szero":{"downloads_url":"plugins/szero.json"},"storm":{"downloads_url":"plugins/storm.json"},"topology":{"downloads_url":"plugins/topology.json"},"starboard":{"downloads_url":"plugins/starboard.json"},"ssm-secret":{"downloads_url":"plugins/ssm-secret.json"},"status":{"downloads_url":"plugins/status.json"},"triage":{"downloads_url":"plugins/triage.json"},"tmux-exec":{"downloads_url":"plugins/tmux-exec.json"},"unlimited":{"downloads_url":"plugins/unlimited.json"},"tap":{"downloads_url":"plugins/tap.json"},"ttsum":{"downloads_url":"plugins/ttsum.json"},"unused-volumes":{"downloads_url":"plugins/unused-volumes.json"},"view-allocations":{"downloads_url":"plugins/view-allocations.json"},"view-quotas":{"downloads_url":"plugins/view-quotas.json"},"viewnode":{"downloads_url":"plugins/viewnode.json"},"view-cert":{"downloads_url":"plugins/view-cert.json"},"validate":{"downloads_url":"plugins/validate.json"},"view-webhook":{"downloads_url":"plugins/view-webhook.json"},"tree":{"downloads_url":"plugins/tree.json"},"tunnel":{"downloads_url":"plugins/tunnel.json"},"support-bundle":{"downloads_url":"plugins/support-bundle.json"},"view-utilization":{"downloads_url":"plugins/view-utilization.json"},"watch-diff":{"downloads_url":"plugins/watch-diff.json"},"vpa-recommendation":{"downloads_url":"plugins/vpa-recommendation.json"},"wait-job":{"downloads_url":"plugins/wait-job.json"},"watch-rollout":{"downloads_url":"plugins/watch-rollout.json"},"volsync":{"downloads_url":"plugins/volsync.json"},"virt":{"downloads_url":"plugins/virt.json"},"view-serviceaccount-kubeconfig":{"downloads_url":"plugins/view-serviceaccount-kubeconfig.json"},"view-secret":{"downloads_url":"plugins/view-secret.json"},"xdsnap":{"downloads_url":"plugins/xdsnap.json"},"whoami":{"downloads_url":"plugins/whoami.json"},"vault-login":{"downloads_url":"plugins/vault-login.json"},"windows-debug":{"downloads_url":"plugins/windows-debug.json"},"wider":{"downloads_url":"plugins/wider.json"},"whisper-secret":{"downloads_url":"plugins/whisper-secret.json"},"wild":{"downloads_url":"plugins/wild.json"},"who-can":{"downloads_url":"plugins/who-can.json"},"warp":{"downloads_url":"plugins/warp.json"}}}
