{"pluginName":"kflow","stats":{"2026-03-28":{"downloads":86},"2026-03-29":{"downloads":86},"2026-03-30":{"downloads":86},"2026-03-31":{"downloads":87},"2026-04-01":{"downloads":89},"2026-04-02":{"downloads":95},"2026-04-03":{"downloads":97},"2026-04-04":{"downloads":98},"2026-04-05":{"downloads":101},"2026-04-06":{"downloads":101},"2026-04-07":{"downloads":101},"2026-04-08":{"downloads":107},"2026-04-09":{"downloads":108},"2026-04-10":{"downloads":111},"2026-04-11":{"downloads":112},"2026-04-12":{"downloads":116},"2026-04-13":{"downloads":121},"2026-04-14":{"downloads":126},"2026-04-15":{"downloads":129},"2026-04-16":{"downloads":131},"2026-04-17":{"downloads":131},"2026-04-18":{"downloads":133},"2026-04-19":{"downloads":134},"2026-04-20":{"downloads":134},"2026-04-21":{"downloads":138},"2026-04-22":{"downloads":139},"2026-04-23":{"downloads":139},"2026-04-24":{"downloads":140},"2026-04-25":{"downloads":141},"2026-04-26":{"downloads":144},"2026-04-27":{"downloads":144},"2026-04-28":{"downloads":145},"2026-04-29":{"downloads":145},"2026-04-30":{"downloads":148},"2026-05-01":{"downloads":151},"2026-05-02":{"downloads":151},"2026-05-03":{"downloads":153},"2026-05-04":{"downloads":153},"2026-05-05":{"downloads":154},"2026-05-06":{"downloads":154},"2026-05-07":{"downloads":155},"2026-05-08":{"downloads":159},"2026-05-09":{"downloads":161},"2026-05-10":{"downloads":164},"2026-05-11":{"downloads":167},"2026-05-12":{"downloads":170},"2026-05-13":{"downloads":170},"2026-05-14":{"downloads":170},"2026-05-15":{"downloads":170},"2026-05-16":{"downloads":171},"2026-05-17":{"downloads":171},"2026-05-18":{"downloads":173},"2026-05-19":{"downloads":173},"2026-05-20":{"downloads":177},"2026-05-21":{"downloads":178},"2026-05-22":{"downloads":178},"2026-05-23":{"downloads":178},"2026-05-24":{"downloads":178},"2026-05-25":{"downloads":178},"2026-05-26":{"downloads":178},"2026-05-28":{"downloads":178},"2026-05-29":{"downloads":178},"2026-05-30":{"downloads":179},"2026-05-31":{"downloads":179},"2026-06-01":{"downloads":179},"2026-06-02":{"downloads":179},"2026-06-03":{"downloads":179},"2026-06-04":{"downloads":179},"2026-06-05":{"downloads":180},"2026-06-06":{"downloads":180},"2026-06-07":{"downloads":181},"2026-06-08":{"downloads":182},"2026-06-09":{"downloads":185},"2026-06-10":{"downloads":188},"2026-06-11":{"downloads":189},"2026-06-12":{"downloads":190},"2026-06-13":{"downloads":190},"2026-06-14":{"downloads":190},"2026-06-15":{"downloads":190},"2026-06-17":{"downloads":191},"2026-06-18":{"downloads":191},"2026-06-20":{"downloads":192},"2026-06-21":{"downloads":192},"2026-06-22":{"downloads":192},"2026-06-23":{"downloads":193},"2026-06-24":{"downloads":193},"2026-06-25":{"downloads":193},"2026-06-26":{"downloads":193},"2026-06-27":{"downloads":193},"2026-06-28":{"downloads":193},"2026-06-29":{"downloads":193},"2026-06-30":{"downloads":193},"2026-07-01":{"downloads":193},"2026-07-02":{"downloads":194}}}